chatflock/__init__.py
chatflock/ai_utils.py
chatflock/backing_stores/__init__.py
chatflock/backing_stores/in_memory.py
chatflock/backing_stores/langchain.py
chatflock/base.py
chatflock/code/__init__.py
chatflock/code/base.py
chatflock/code/docker.py
chatflock/code/langchain.py
chatflock/code/local.py
chatflock/composition_generators/__init__.py
chatflock/composition_generators/langchain.py
chatflock/conductors/__init__.py
chatflock/conductors/langchain.py
chatflock/conductors/round_robin.py
chatflock/errors.py
chatflock/parsing_utils.py
chatflock/participants/__init__.py
chatflock/participants/group.py
chatflock/participants/langchain.py
chatflock/participants/output_parser.py
chatflock/participants/spr.py
chatflock/participants/user.py
chatflock/renderers/__init__.py
chatflock/renderers/terminal.py
chatflock/sequencial_process/__init__.py
chatflock/sequencial_process/sequential_process.py
chatflock/structured_string.py
chatflock/use_cases/__init__.py
chatflock/use_cases/bshr.py
chatflock/use_cases/request_response.py
chatflock/utils.py
chatflock/web_research/__init__.py
chatflock/web_research/errors.py
chatflock/web_research/page_analyzer.py
chatflock/web_research/page_retrievers/__init__.py
chatflock/web_research/page_retrievers/base.py
chatflock/web_research/page_retrievers/fallback.py
chatflock/web_research/page_retrievers/requests_retriever.py
chatflock/web_research/page_retrievers/scraper_api_retriever.py
chatflock/web_research/page_retrievers/selenium_retriever.py
chatflock/web_research/search.py
chatflock/web_research/web_research.py
chat_flock-0.1.2.dist-info/LICENSE
chat_flock-0.1.2.dist-info/METADATA
chat_flock-0.1.2.dist-info/WHEEL
chat_flock-0.1.2.dist-info/RECORD
