Metadata-Version: 2.1
Name: chat-flock
Version: 0.1.2
Summary: Driving Dynamic Multi-Participant Chat Interactions for AI and Human Discourse
Home-page: https://github.com/doodledood/chat-flock
License: MIT
Keywords: chat,chatbot,openai,llm,generative-ai,langchain
Author: chat-flock
Author-email: hello@chat-flock.com
Requires-Python: >=3.9.0,<4.0.0
Classifier: Development Status :: 3 - Alpha
Classifier: Intended Audience :: Developers
Classifier: License :: OSI Approved :: MIT License
Classifier: Operating System :: OS Independent
Classifier: Programming Language :: Python :: 3
Classifier: Programming Language :: Python :: 3.9
Classifier: Programming Language :: Python :: 3.10
Classifier: Programming Language :: Python :: 3.11
Classifier: Programming Language :: Python :: 3.12
Classifier: Topic :: Software Development :: Libraries :: Python Modules
Requires-Dist: beautifulsoup4 (>=4.12.2,<5.0.0)
Requires-Dist: docker (>=6.1.3,<7.0.0)
Requires-Dist: halo (>=0.0.31,<0.0.32)
Requires-Dist: importlib_metadata (>=6.8.0,<7.0.0)
Requires-Dist: langchain (>=0.0.335,<0.0.336)
Requires-Dist: openai (>=1.2.3,<2.0.0)
Requires-Dist: pydantic (>=2.4.2,<3.0.0)
Requires-Dist: python-dotenv (>=1.0.0,<2.0.0)
Requires-Dist: questionary (>=2.0.1,<3.0.0)
Requires-Dist: requests (>=2.31.0,<3.0.0)
Requires-Dist: tenacity (>=8.2.3,<9.0.0)
Requires-Dist: tiktoken (>=0.5.1,<0.6.0)
Requires-Dist: tqdm (>=4.66.1,<5.0.0)
Project-URL: Repository, https://github.com/doodledood/chat-flock
